insurance/Emblem01.py
insurance/EmblemV01.py
insurance/__init__.py
insurance/auto_group_run.py
insurance/auto_pricing_techincal_groupping.py
insurance/cant_use_.py
insurance/cant_use_ins.py
insurance/fix_bug_.py
insurance/fix_bug_ins.py
insurance/remove_large_loss.py
insurance/sandbox1_.py
insurance_tool-0.1.0.dist-info/METADATA
insurance_tool-0.1.0.dist-info/WHEEL
insurance_tool-0.1.0.dist-info/top_level.txt
insurance_tool-0.1.0.dist-info/RECORD
