Metadata-Version: 2.1
Name: insurance-tool
Version: 0.1.0
Summary: <add short describtion here>
Home-page: UNKNOWN
Author: Dear Norathee
License: MIT
Platform: UNKNOWN
Requires-Dist: xlwings
